mq_misc/__init__.py
mq_misc/amqp.py
mq_misc/errors.py
mq_misc/consume/__init__.py
mq_misc/consume/__main__.py
mq_misc/publish/__init__.py
mq_misc/publish/__main__.py
mq_misc-0.0.10.dist-info/licenses/LICENSE
mq_misc-0.0.10.dist-info/METADATA
mq_misc-0.0.10.dist-info/WHEEL
mq_misc-0.0.10.dist-info/top_level.txt
mq_misc-0.0.10.dist-info/RECORD
