Metadata-Version: 2.4
Name: mq-misc
Version: 0.0.10
Summary: Utility package for working with rabbitmq
Author: Anton Gorinenko
Author-email: anton.gorinenko@gmail.com
Keywords: python,asyncio,utils,mq,aio_pika,rabbit mq,rabbit
Classifier: Programming Language :: Python :: 3.8
Classifier: Operating System :: OS Independent
Requires-Python: >=3.8
License-File: LICENSE
Requires-Dist: aio_pika>=6.8.0
Requires-Dist: ConfigArgParse>=1.3
Provides-Extra: test
Requires-Dist: pytest; extra == "test"
Requires-Dist: pytest-cov; extra == "test"
Requires-Dist: pytest-asyncio; extra == "test"
Requires-Dist: pytest-mock; extra == "test"
Requires-Dist: pylint; extra == "test"
Requires-Dist: pytest-dotenv; extra == "test"
Requires-Dist: envparse; extra == "test"
Requires-Dist: asynctest; extra == "test"
Dynamic: author
Dynamic: author-email
Dynamic: classifier
Dynamic: description
Dynamic: description-content-type
Dynamic: keywords
Dynamic: license-file
Dynamic: provides-extra
Dynamic: requires-dist
Dynamic: requires-python
Dynamic: summary
